{
  "displayColumn": "name",
  "isReactive": true,
  "meta": {
    "createdDate": {
      "displayName": "Created Date",
      "invisible": true,
      "order": 3,
      "type": "date"
    },
    "dESCRIPTION": {
      "displayName": "dESCRIPTION",
      "order": 12,
      "type": "string"
    },
    "dOCUMENTPREVIEW": {
      "displayName": "dOCUMENTPREVIEW",
      "order": 9,
      "type": "profile_image"
    },
    "iTEMNO": {
      "displayName": "iTEMNO",
      "order": 10,
      "type": "number"
    },
    "image": {
      "displayName": "image",
      "order": 8,
      "type": "profile_image"
    },
    "lastEditDate": {
      "displayName": "Last edit date",
      "invisible": true,
      "order": 7,
      "type": "date"
    },
    "lastEditedBy": {
      "displayName": "Last edited by",
      "invisible": true,
      "order": 6,
      "type": "user"
    },
    "layout": {
      "displayName": "Layout",
      "invisible": true,
      "order": 1,
      "type": "select"
    },
    "material": {
      "displayName": "material",
      "order": 13,
      "type": "string"
    },
    "name": {
      "displayName": "Name",
      "order": 0,
      "type": "string"
    },
    "nextEvents": {
      "displayName": "Next Events",
      "invisible": true,
      "order": 5,
      "type": "string"
    },
    "operations": {
      "displayName": "operations",
      "order": 15,
      "type": "string"
    },
    "owner": {
      "displayName": "Owner",
      "invisible": true,
      "order": 2,
      "type": "user"
    },
    "pARTNUMBER": {
      "displayName": "pARTNUMBER",
      "order": 11,
      "type": "string"
    },
    "qTY": {
      "displayName": "qTY",
      "order": 14,
      "type": "number"
    },
    "state": {
      "displayName": "State",
      "invisible": true,
      "order": 4,
      "type": "string"
    }
  },
  "rowEditorFieldsForm": {
    "sections": [
      {
        "name": "section_292847",
        "label": "",
        "clientKey": "section_292847",
        "order": 0,
        "rows": [
          {
            "name": "section_292847_row_266027",
            "label": "",
            "order": 0,
            "controls": [
              {
                "type": "text",
                "name": "control_fad0fb52-3106-11f0-bcfe-05add1174dfb",
                "fieldName": "control_fad0fb52-3106-11f0-bcfe-05add1174dfb",
                "label": "Name",
                "order": 0,
                "defaultValue": "",
                "value": "",
                "className": "col-md-6",
                "useWidthPercentages": false,
                "widthPercentages": null,
                "readonly": false,
                "readonlyCondition": "",
                "placeholder": "",
                "required": false,
                "requiredCondition": "",
                "isMultiLine": false,
                "isInteger": false,
                "decimalPlace": 2,
                "expression": "",
                "additionalFilter": "",
                "oneDriveFileId": null,
                "isTodayValue": false,
                "isTodayValueCreated": true,
                "dateFormat": "mm/dd/yy hh:mm p",
                "timezone": null,
                "selectedDataGrid": null,
                "printedFileName": null,
                "dataFetchDepth": "basic",
                "buttonLabel": "",
                "dataForTemplate": null,
                "selectedOutputDataGrid": null,
                "templateRowKey": null,
                "isForDownload": true,
                "isOneDriveTemplate": false,
                "selectedOneDriveFile": null,
                "openInNewTab": true,
                "attachRecord": false,
                "isCurrentUser": false,
                "isCurrentUserOwner": true,
                "isNowTimeValue": false,
                "timeFormat": "HH:mm",
                "isMultiple": false,
                "isAjax": false,
                "dataOptions": [],
                "ajaxDataUrl": "",
                "isChecked": false,
                "vif": "",
                "customCode": "",
                "invisible": false,
                "invisibleCondition": "",
                "invisibleLabel": false,
                "enableCustomValidation": false,
                "customValidationRule": "",
                "customValidationErrorMessage": "",
                "mask": "",
                "lookupOpenInModalDisabled": false,
                "preventModalShowUpWhenNewItemAdded": false,
                "lookUpSearch": null,
                "editorMode": "javascript",
                "dataGridAvailableViews": [],
                "dataGridView": null,
                "dataGridAddRecordsText": "",
                "dataGridAddRecordText": "",
                "skipCrop": false,
                "disableRoundedStyle": false,
                "attachedFunction": "",
                "buttonText": "",
                "buttonVariant": "primary",
                "customClassName": "",
                "propName": "name"
              },
              {
                "type": "profile_image",
                "name": "control_0020ff60-3107-11f0-bcfe-05add1174dfb",
                "fieldName": "control_0020ff60-3107-11f0-bcfe-05add1174dfb",
                "label": "image",
                "order": 0,
                "defaultValue": "",
                "value": "",
                "className": "col-md-6",
                "useWidthPercentages": false,
                "widthPercentages": null,
                "readonly": false,
                "readonlyCondition": "",
                "placeholder": "",
                "required": false,
                "requiredCondition": "",
                "isMultiLine": false,
                "isInteger": false,
                "decimalPlace": 2,
                "expression": "",
                "additionalFilter": "",
                "oneDriveFileId": null,
                "isTodayValue": false,
                "isTodayValueCreated": true,
                "dateFormat": "mm/dd/yy hh:mm p",
                "timezone": null,
                "selectedDataGrid": null,
                "printedFileName": null,
                "dataFetchDepth": "basic",
                "buttonLabel": "",
                "dataForTemplate": null,
                "selectedOutputDataGrid": null,
                "templateRowKey": null,
                "isForDownload": true,
                "isOneDriveTemplate": false,
                "selectedOneDriveFile": null,
                "openInNewTab": true,
                "attachRecord": false,
                "isCurrentUser": false,
                "isCurrentUserOwner": true,
                "isNowTimeValue": false,
                "timeFormat": "HH:mm",
                "isMultiple": false,
                "isAjax": false,
                "dataOptions": [],
                "ajaxDataUrl": "",
                "isChecked": false,
                "vif": "",
                "customCode": "",
                "invisible": false,
                "invisibleCondition": "",
                "invisibleLabel": false,
                "enableCustomValidation": false,
                "customValidationRule": "",
                "customValidationErrorMessage": "",
                "mask": "",
                "lookupOpenInModalDisabled": false,
                "preventModalShowUpWhenNewItemAdded": false,
                "lookUpSearch": null,
                "editorMode": "javascript",
                "dataGridAvailableViews": [],
                "dataGridView": null,
                "dataGridAddRecordsText": "",
                "dataGridAddRecordText": "",
                "skipCrop": false,
                "disableRoundedStyle": false,
                "attachedFunction": "",
                "buttonText": "",
                "buttonVariant": "primary",
                "customClassName": "",
                "propName": "image"
              },
              {
                "type": "profile_image",
                "name": "control_2f306c00-3107-11f0-bcfe-05add1174dfb",
                "fieldName": "control_2f306c00-3107-11f0-bcfe-05add1174dfb",
                "label": "dOCUMENTPREVIEW",
                "order": 0,
                "defaultValue": "",
                "value": "",
                "className": "col-md-6",
                "useWidthPercentages": false,
                "widthPercentages": null,
                "readonly": false,
                "readonlyCondition": "",
                "placeholder": "",
                "required": false,
                "requiredCondition": "",
                "isMultiLine": false,
                "isInteger": false,
                "decimalPlace": 2,
                "expression": "",
                "additionalFilter": "",
                "oneDriveFileId": null,
                "isTodayValue": false,
                "isTodayValueCreated": true,
                "dateFormat": "mm/dd/yy hh:mm p",
                "timezone": null,
                "selectedDataGrid": null,
                "printedFileName": null,
                "dataFetchDepth": "basic",
                "buttonLabel": "",
                "dataForTemplate": null,
                "selectedOutputDataGrid": null,
                "templateRowKey": null,
                "isForDownload": true,
                "isOneDriveTemplate": false,
                "selectedOneDriveFile": null,
                "openInNewTab": true,
                "attachRecord": false,
                "isCurrentUser": false,
                "isCurrentUserOwner": true,
                "isNowTimeValue": false,
                "timeFormat": "HH:mm",
                "isMultiple": false,
                "isAjax": false,
                "dataOptions": [],
                "ajaxDataUrl": "",
                "isChecked": false,
                "vif": "",
                "customCode": "",
                "invisible": false,
                "invisibleCondition": "",
                "invisibleLabel": false,
                "enableCustomValidation": false,
                "customValidationRule": "",
                "customValidationErrorMessage": "",
                "mask": "",
                "lookupOpenInModalDisabled": false,
                "preventModalShowUpWhenNewItemAdded": false,
                "lookUpSearch": null,
                "editorMode": "javascript",
                "dataGridAvailableViews": [],
                "dataGridView": null,
                "dataGridAddRecordsText": "",
                "dataGridAddRecordText": "",
                "skipCrop": false,
                "disableRoundedStyle": false,
                "attachedFunction": "",
                "buttonText": "",
                "buttonVariant": "primary",
                "customClassName": "",
                "propName": "dOCUMENTPREVIEW"
              },
              {
                "type": "number",
                "name": "control_2fb9c040-3107-11f0-bcfe-05add1174dfb",
                "fieldName": "control_2fb9c040-3107-11f0-bcfe-05add1174dfb",
                "label": "iTEMNO",
                "order": 0,
                "defaultValue": "",
                "value": "",
                "className": "col-md-6",
                "useWidthPercentages": false,
                "widthPercentages": null,
                "readonly": false,
                "readonlyCondition": "",
                "placeholder": "",
                "required": false,
                "requiredCondition": "",
                "isMultiLine": false,
                "isInteger": false,
                "decimalPlace": 2,
                "expression": "",
                "additionalFilter": "",
                "oneDriveFileId": null,
                "isTodayValue": false,
                "isTodayValueCreated": true,
                "dateFormat": "mm/dd/yy hh:mm p",
                "timezone": null,
                "selectedDataGrid": null,
                "printedFileName": null,
                "dataFetchDepth": "basic",
                "buttonLabel": "",
                "dataForTemplate": null,
                "selectedOutputDataGrid": null,
                "templateRowKey": null,
                "isForDownload": true,
                "isOneDriveTemplate": false,
                "selectedOneDriveFile": null,
                "openInNewTab": true,
                "attachRecord": false,
                "isCurrentUser": false,
                "isCurrentUserOwner": true,
                "isNowTimeValue": false,
                "timeFormat": "HH:mm",
                "isMultiple": false,
                "isAjax": false,
                "dataOptions": [],
                "ajaxDataUrl": "",
                "isChecked": false,
                "vif": "",
                "customCode": "",
                "invisible": false,
                "invisibleCondition": "",
                "invisibleLabel": false,
                "enableCustomValidation": false,
                "customValidationRule": "",
                "customValidationErrorMessage": "",
                "mask": "",
                "lookupOpenInModalDisabled": false,
                "preventModalShowUpWhenNewItemAdded": false,
                "lookUpSearch": null,
                "editorMode": "javascript",
                "dataGridAvailableViews": [],
                "dataGridView": null,
                "dataGridAddRecordsText": "",
                "dataGridAddRecordText": "",
                "skipCrop": false,
                "disableRoundedStyle": false,
                "attachedFunction": "",
                "buttonText": "",
                "buttonVariant": "primary",
                "customClassName": "",
                "propName": "iTEMNO"
              },
              {
                "type": "text",
                "name": "control_30377bc0-3107-11f0-bcfe-05add1174dfb",
                "fieldName": "control_30377bc0-3107-11f0-bcfe-05add1174dfb",
                "label": "pARTNUMBER",
                "order": 0,
                "defaultValue": "",
                "value": "",
                "className": "col-md-6",
                "useWidthPercentages": false,
                "widthPercentages": null,
                "readonly": false,
                "readonlyCondition": "",
                "placeholder": "",
                "required": false,
                "requiredCondition": "",
                "isMultiLine": false,
                "isInteger": false,
                "decimalPlace": 2,
                "expression": "",
                "additionalFilter": "",
                "oneDriveFileId": null,
                "isTodayValue": false,
                "isTodayValueCreated": true,
                "dateFormat": "mm/dd/yy hh:mm p",
                "timezone": null,
                "selectedDataGrid": null,
                "printedFileName": null,
                "dataFetchDepth": "basic",
                "buttonLabel": "",
                "dataForTemplate": null,
                "selectedOutputDataGrid": null,
                "templateRowKey": null,
                "isForDownload": true,
                "isOneDriveTemplate": false,
                "selectedOneDriveFile": null,
                "openInNewTab": true,
                "attachRecord": false,
                "isCurrentUser": false,
                "isCurrentUserOwner": true,
                "isNowTimeValue": false,
                "timeFormat": "HH:mm",
                "isMultiple": false,
                "isAjax": false,
                "dataOptions": [],
                "ajaxDataUrl": "",
                "isChecked": false,
                "vif": "",
                "customCode": "",
                "invisible": false,
                "invisibleCondition": "",
                "invisibleLabel": false,
                "enableCustomValidation": false,
                "customValidationRule": "",
                "customValidationErrorMessage": "",
                "mask": "",
                "lookupOpenInModalDisabled": false,
                "preventModalShowUpWhenNewItemAdded": false,
                "lookUpSearch": null,
                "editorMode": "javascript",
                "dataGridAvailableViews": [],
                "dataGridView": null,
                "dataGridAddRecordsText": "",
                "dataGridAddRecordText": "",
                "skipCrop": false,
                "disableRoundedStyle": false,
                "attachedFunction": "",
                "buttonText": "",
                "buttonVariant": "primary",
                "customClassName": "",
                "propName": "pARTNUMBER"
              },
              {
                "type": "text",
                "name": "control_30a2e7c0-3107-11f0-bcfe-05add1174dfb",
                "fieldName": "control_30a2e7c0-3107-11f0-bcfe-05add1174dfb",
                "label": "dESCRIPTION",
                "order": 0,
                "defaultValue": "",
                "value": "",
                "className": "col-md-6",
                "useWidthPercentages": false,
                "widthPercentages": null,
                "readonly": false,
                "readonlyCondition": "",
                "placeholder": "",
                "required": false,
                "requiredCondition": "",
                "isMultiLine": false,
                "isInteger": false,
                "decimalPlace": 2,
                "expression": "",
                "additionalFilter": "",
                "oneDriveFileId": null,
                "isTodayValue": false,
                "isTodayValueCreated": true,
                "dateFormat": "mm/dd/yy hh:mm p",
                "timezone": null,
                "selectedDataGrid": null,
                "printedFileName": null,
                "dataFetchDepth": "basic",
                "buttonLabel": "",
                "dataForTemplate": null,
                "selectedOutputDataGrid": null,
                "templateRowKey": null,
                "isForDownload": true,
                "isOneDriveTemplate": false,
                "selectedOneDriveFile": null,
                "openInNewTab": true,
                "attachRecord": false,
                "isCurrentUser": false,
                "isCurrentUserOwner": true,
                "isNowTimeValue": false,
                "timeFormat": "HH:mm",
                "isMultiple": false,
                "isAjax": false,
                "dataOptions": [],
                "ajaxDataUrl": "",
                "isChecked": false,
                "vif": "",
                "customCode": "",
                "invisible": false,
                "invisibleCondition": "",
                "invisibleLabel": false,
                "enableCustomValidation": false,
                "customValidationRule": "",
                "customValidationErrorMessage": "",
                "mask": "",
                "lookupOpenInModalDisabled": false,
                "preventModalShowUpWhenNewItemAdded": false,
                "lookUpSearch": null,
                "editorMode": "javascript",
                "dataGridAvailableViews": [],
                "dataGridView": null,
                "dataGridAddRecordsText": "",
                "dataGridAddRecordText": "",
                "skipCrop": false,
                "disableRoundedStyle": false,
                "attachedFunction": "",
                "buttonText": "",
                "buttonVariant": "primary",
                "customClassName": "",
                "propName": "dESCRIPTION"
              },
              {
                "type": "text",
                "name": "control_31169120-3107-11f0-bcfe-05add1174dfb",
                "fieldName": "control_31169120-3107-11f0-bcfe-05add1174dfb",
                "label": "material",
                "order": 0,
                "defaultValue": "",
                "value": "",
                "className": "col-md-6",
                "useWidthPercentages": false,
                "widthPercentages": null,
                "readonly": false,
                "readonlyCondition": "",
                "placeholder": "",
                "required": false,
                "requiredCondition": "",
                "isMultiLine": false,
                "isInteger": false,
                "decimalPlace": 2,
                "expression": "",
                "additionalFilter": "",
                "oneDriveFileId": null,
                "isTodayValue": false,
                "isTodayValueCreated": true,
                "dateFormat": "mm/dd/yy hh:mm p",
                "timezone": null,
                "selectedDataGrid": null,
                "printedFileName": null,
                "dataFetchDepth": "basic",
                "buttonLabel": "",
                "dataForTemplate": null,
                "selectedOutputDataGrid": null,
                "templateRowKey": null,
                "isForDownload": true,
                "isOneDriveTemplate": false,
                "selectedOneDriveFile": null,
                "openInNewTab": true,
                "attachRecord": false,
                "isCurrentUser": false,
                "isCurrentUserOwner": true,
                "isNowTimeValue": false,
                "timeFormat": "HH:mm",
                "isMultiple": false,
                "isAjax": false,
                "dataOptions": [],
                "ajaxDataUrl": "",
                "isChecked": false,
                "vif": "",
                "customCode": "",
                "invisible": false,
                "invisibleCondition": "",
                "invisibleLabel": false,
                "enableCustomValidation": false,
                "customValidationRule": "",
                "customValidationErrorMessage": "",
                "mask": "",
                "lookupOpenInModalDisabled": false,
                "preventModalShowUpWhenNewItemAdded": false,
                "lookUpSearch": null,
                "editorMode": "javascript",
                "dataGridAvailableViews": [],
                "dataGridView": null,
                "dataGridAddRecordsText": "",
                "dataGridAddRecordText": "",
                "skipCrop": false,
                "disableRoundedStyle": false,
                "attachedFunction": "",
                "buttonText": "",
                "buttonVariant": "primary",
                "customClassName": "",
                "propName": "material"
              },
              {
                "type": "number",
                "name": "control_3183d1e0-3107-11f0-bcfe-05add1174dfb",
                "fieldName": "control_3183d1e0-3107-11f0-bcfe-05add1174dfb",
                "label": "qTY",
                "order": 0,
                "defaultValue": "",
                "value": "",
                "className": "col-md-6",
                "useWidthPercentages": false,
                "widthPercentages": null,
                "readonly": false,
                "readonlyCondition": "",
                "placeholder": "",
                "required": false,
                "requiredCondition": "",
                "isMultiLine": false,
                "isInteger": false,
                "decimalPlace": 2,
                "expression": "",
                "additionalFilter": "",
                "oneDriveFileId": null,
                "isTodayValue": false,
                "isTodayValueCreated": true,
                "dateFormat": "mm/dd/yy hh:mm p",
                "timezone": null,
                "selectedDataGrid": null,
                "printedFileName": null,
                "dataFetchDepth": "basic",
                "buttonLabel": "",
                "dataForTemplate": null,
                "selectedOutputDataGrid": null,
                "templateRowKey": null,
                "isForDownload": true,
                "isOneDriveTemplate": false,
                "selectedOneDriveFile": null,
                "openInNewTab": true,
                "attachRecord": false,
                "isCurrentUser": false,
                "isCurrentUserOwner": true,
                "isNowTimeValue": false,
                "timeFormat": "HH:mm",
                "isMultiple": false,
                "isAjax": false,
                "dataOptions": [],
                "ajaxDataUrl": "",
                "isChecked": false,
                "vif": "",
                "customCode": "",
                "invisible": false,
                "invisibleCondition": "",
                "invisibleLabel": false,
                "enableCustomValidation": false,
                "customValidationRule": "",
                "customValidationErrorMessage": "",
                "mask": "",
                "lookupOpenInModalDisabled": false,
                "preventModalShowUpWhenNewItemAdded": false,
                "lookUpSearch": null,
                "editorMode": "javascript",
                "dataGridAvailableViews": [],
                "dataGridView": null,
                "dataGridAddRecordsText": "",
                "dataGridAddRecordText": "",
                "skipCrop": false,
                "disableRoundedStyle": false,
                "attachedFunction": "",
                "buttonText": "",
                "buttonVariant": "primary",
                "customClassName": "",
                "propName": "qTY"
              },
              {
                "type": "text",
                "name": "control_81cd1a80-3107-11f0-9368-010bdaf6b03d",
                "fieldName": "control_81cd1a80-3107-11f0-9368-010bdaf6b03d",
                "label": "operations",
                "order": 0,
                "defaultValue": "",
                "value": "",
                "className": "col-md-6",
                "useWidthPercentages": false,
                "widthPercentages": null,
                "readonly": false,
                "readonlyCondition": "",
                "placeholder": "",
                "required": false,
                "requiredCondition": "",
                "isMultiLine": false,
                "isInteger": false,
                "decimalPlace": 2,
                "expression": "",
                "additionalFilter": "",
                "oneDriveFileId": null,
                "isTodayValue": false,
                "isTodayValueCreated": true,
                "dateFormat": "mm/dd/yy hh:mm p",
                "timezone": null,
                "selectedDataGrid": null,
                "printedFileName": null,
                "dataFetchDepth": "basic",
                "buttonLabel": "",
                "dataForTemplate": null,
                "selectedOutputDataGrid": null,
                "templateRowKey": null,
                "isForDownload": true,
                "isOneDriveTemplate": false,
                "selectedOneDriveFile": null,
                "openInNewTab": true,
                "attachRecord": false,
                "isCurrentUser": false,
                "isCurrentUserOwner": true,
                "isNowTimeValue": false,
                "timeFormat": "HH:mm",
                "isMultiple": false,
                "isAjax": false,
                "dataOptions": [],
                "ajaxDataUrl": "",
                "isChecked": false,
                "vif": "",
                "customCode": "",
                "invisible": false,
                "invisibleCondition": "",
                "invisibleLabel": false,
                "enableCustomValidation": false,
                "customValidationRule": "",
                "customValidationErrorMessage": "",
                "mask": "",
                "lookupOpenInModalDisabled": false,
                "preventModalShowUpWhenNewItemAdded": false,
                "lookUpSearch": null,
                "editorMode": "javascript",
                "dataGridAvailableViews": [],
                "dataGridView": null,
                "dataGridAddRecordsText": "",
                "dataGridAddRecordText": "",
                "skipCrop": false,
                "disableRoundedStyle": false,
                "attachedFunction": "",
                "buttonText": "",
                "buttonVariant": "primary",
                "customClassName": "",
                "propName": "operations"
              }
            ]
          }
        ],
        "labelPosition": "top",
        "isDynamic": false,
        "minInstance": 1,
        "maxInstance": 0,
        "instances": []
      },
      {
        "cleintKey": "hidden_section_fad0fb50-3106-11f0-bcfe-05add1174dfb",
        "instances": [],
        "isDynamic": false,
        "label": "Hidden Section",
        "vif": "false",
        "name": "hidden_section_fad0fb50-3106-11f0-bcfe-05add1174dfb",
        "order": 1,
        "rows": [
          {
            "name": "hidden_section_fad0fb50-3106-11f0-bcfe-05add1174dfb_row_fad0fb51-3106-11f0-bcfe-05add1174dfb",
            "controls": [
              {
                "type": "select",
                "name": "control_faf1a2b0-3106-11f0-bcfe-05add1174dfb",
                "fieldName": "control_faf1a2b0-3106-11f0-bcfe-05add1174dfb",
                "label": "Layout",
                "order": 0,
                "defaultValue": "",
                "value": "",
                "className": "col-md-6",
                "useWidthPercentages": false,
                "widthPercentages": null,
                "readonly": false,
                "readonlyCondition": "",
                "placeholder": "",
                "required": false,
                "requiredCondition": "",
                "isMultiLine": false,
                "isInteger": false,
                "decimalPlace": 2,
                "expression": "",
                "additionalFilter": "",
                "oneDriveFileId": null,
                "isTodayValue": false,
                "isTodayValueCreated": true,
                "dateFormat": "mm/dd/yy hh:mm p",
                "timezone": null,
                "selectedDataGrid": null,
                "printedFileName": null,
                "dataFetchDepth": "basic",
                "buttonLabel": "",
                "dataForTemplate": null,
                "selectedOutputDataGrid": null,
                "templateRowKey": null,
                "isForDownload": true,
                "isOneDriveTemplate": false,
                "selectedOneDriveFile": null,
                "openInNewTab": true,
                "attachRecord": false,
                "isCurrentUser": false,
                "isCurrentUserOwner": true,
                "isNowTimeValue": false,
                "timeFormat": "HH:mm",
                "isMultiple": false,
                "isAjax": false,
                "dataOptions": [],
                "ajaxDataUrl": "",
                "isChecked": false,
                "vif": "",
                "customCode": "",
                "invisible": true,
                "invisibleCondition": "",
                "invisibleLabel": false,
                "enableCustomValidation": false,
                "customValidationRule": "",
                "customValidationErrorMessage": "",
                "mask": "",
                "lookupOpenInModalDisabled": false,
                "preventModalShowUpWhenNewItemAdded": false,
                "lookUpSearch": null,
                "editorMode": "javascript",
                "dataGridAvailableViews": [],
                "dataGridView": null,
                "dataGridAddRecordsText": "",
                "dataGridAddRecordText": "",
                "skipCrop": false,
                "disableRoundedStyle": false,
                "attachedFunction": "",
                "buttonText": "",
                "buttonVariant": "primary",
                "customClassName": "",
                "propName": "layout"
              },
              {
                "type": "user",
                "name": "control_fb109c60-3106-11f0-bcfe-05add1174dfb",
                "fieldName": "control_fb109c60-3106-11f0-bcfe-05add1174dfb",
                "label": "Owner",
                "order": 0,
                "defaultValue": "",
                "value": "",
                "className": "col-md-6",
                "useWidthPercentages": false,
                "widthPercentages": null,
                "readonly": false,
                "readonlyCondition": "",
                "placeholder": "",
                "required": false,
                "requiredCondition": "",
                "isMultiLine": false,
                "isInteger": false,
                "decimalPlace": 2,
                "expression": "",
                "additionalFilter": "",
                "oneDriveFileId": null,
                "isTodayValue": false,
                "isTodayValueCreated": true,
                "dateFormat": "mm/dd/yy hh:mm p",
                "timezone": null,
                "selectedDataGrid": null,
                "printedFileName": null,
                "dataFetchDepth": "basic",
                "buttonLabel": "",
                "dataForTemplate": null,
                "selectedOutputDataGrid": null,
                "templateRowKey": null,
                "isForDownload": true,
                "isOneDriveTemplate": false,
                "selectedOneDriveFile": null,
                "openInNewTab": true,
                "attachRecord": false,
                "isCurrentUser": false,
                "isCurrentUserOwner": true,
                "isNowTimeValue": false,
                "timeFormat": "HH:mm",
                "isMultiple": false,
                "isAjax": false,
                "dataOptions": [],
                "ajaxDataUrl": "",
                "isChecked": false,
                "vif": "",
                "customCode": "",
                "invisible": true,
                "invisibleCondition": "",
                "invisibleLabel": false,
                "enableCustomValidation": false,
                "customValidationRule": "",
                "customValidationErrorMessage": "",
                "mask": "",
                "lookupOpenInModalDisabled": false,
                "preventModalShowUpWhenNewItemAdded": false,
                "lookUpSearch": null,
                "editorMode": "javascript",
                "dataGridAvailableViews": [],
                "dataGridView": null,
                "dataGridAddRecordsText": "",
                "dataGridAddRecordText": "",
                "skipCrop": false,
                "disableRoundedStyle": false,
                "attachedFunction": "",
                "buttonText": "",
                "buttonVariant": "primary",
                "customClassName": "",
                "propName": "owner"
              },
              {
                "type": "datepicker",
                "name": "control_fb2f6f00-3106-11f0-bcfe-05add1174dfb",
                "fieldName": "control_fb2f6f00-3106-11f0-bcfe-05add1174dfb",
                "label": "Created Date",
                "order": 0,
                "defaultValue": "",
                "value": "",
                "className": "col-md-6",
                "useWidthPercentages": false,
                "widthPercentages": null,
                "readonly": false,
                "readonlyCondition": "",
                "placeholder": "",
                "required": false,
                "requiredCondition": "",
                "isMultiLine": false,
                "isInteger": false,
                "decimalPlace": 2,
                "expression": "",
                "additionalFilter": "",
                "oneDriveFileId": null,
                "isTodayValue": false,
                "isTodayValueCreated": true,
                "dateFormat": "mm/dd/yy hh:mm p",
                "timezone": null,
                "selectedDataGrid": null,
                "printedFileName": null,
                "dataFetchDepth": "basic",
                "buttonLabel": "",
                "dataForTemplate": null,
                "selectedOutputDataGrid": null,
                "templateRowKey": null,
                "isForDownload": true,
                "isOneDriveTemplate": false,
                "selectedOneDriveFile": null,
                "openInNewTab": true,
                "attachRecord": false,
                "isCurrentUser": false,
                "isCurrentUserOwner": true,
                "isNowTimeValue": false,
                "timeFormat": "HH:mm",
                "isMultiple": false,
                "isAjax": false,
                "dataOptions": [],
                "ajaxDataUrl": "",
                "isChecked": false,
                "vif": "",
                "customCode": "",
                "invisible": true,
                "invisibleCondition": "",
                "invisibleLabel": false,
                "enableCustomValidation": false,
                "customValidationRule": "",
                "customValidationErrorMessage": "",
                "mask": "",
                "lookupOpenInModalDisabled": false,
                "preventModalShowUpWhenNewItemAdded": false,
                "lookUpSearch": null,
                "editorMode": "javascript",
                "dataGridAvailableViews": [],
                "dataGridView": null,
                "dataGridAddRecordsText": "",
                "dataGridAddRecordText": "",
                "skipCrop": false,
                "disableRoundedStyle": false,
                "attachedFunction": "",
                "buttonText": "",
                "buttonVariant": "primary",
                "customClassName": "",
                "propName": "createdDate"
              },
              {
                "type": "text",
                "name": "control_fb4edde0-3106-11f0-bcfe-05add1174dfb",
                "fieldName": "control_fb4edde0-3106-11f0-bcfe-05add1174dfb",
                "label": "State",
                "order": 0,
                "defaultValue": "",
                "value": "",
                "className": "col-md-6",
                "useWidthPercentages": false,
                "widthPercentages": null,
                "readonly": false,
                "readonlyCondition": "",
                "placeholder": "",
                "required": false,
                "requiredCondition": "",
                "isMultiLine": false,
                "isInteger": false,
                "decimalPlace": 2,
                "expression": "",
                "additionalFilter": "",
                "oneDriveFileId": null,
                "isTodayValue": false,
                "isTodayValueCreated": true,
                "dateFormat": "mm/dd/yy hh:mm p",
                "timezone": null,
                "selectedDataGrid": null,
                "printedFileName": null,
                "dataFetchDepth": "basic",
                "buttonLabel": "",
                "dataForTemplate": null,
                "selectedOutputDataGrid": null,
                "templateRowKey": null,
                "isForDownload": true,
                "isOneDriveTemplate": false,
                "selectedOneDriveFile": null,
                "openInNewTab": true,
                "attachRecord": false,
                "isCurrentUser": false,
                "isCurrentUserOwner": true,
                "isNowTimeValue": false,
                "timeFormat": "HH:mm",
                "isMultiple": false,
                "isAjax": false,
                "dataOptions": [],
                "ajaxDataUrl": "",
                "isChecked": false,
                "vif": "",
                "customCode": "",
                "invisible": true,
                "invisibleCondition": "",
                "invisibleLabel": false,
                "enableCustomValidation": false,
                "customValidationRule": "",
                "customValidationErrorMessage": "",
                "mask": "",
                "lookupOpenInModalDisabled": false,
                "preventModalShowUpWhenNewItemAdded": false,
                "lookUpSearch": null,
                "editorMode": "javascript",
                "dataGridAvailableViews": [],
                "dataGridView": null,
                "dataGridAddRecordsText": "",
                "dataGridAddRecordText": "",
                "skipCrop": false,
                "disableRoundedStyle": false,
                "attachedFunction": "",
                "buttonText": "",
                "buttonVariant": "primary",
                "customClassName": "",
                "propName": "state"
              },
              {
                "type": "text",
                "name": "control_fb704890-3106-11f0-bcfe-05add1174dfb",
                "fieldName": "control_fb704890-3106-11f0-bcfe-05add1174dfb",
                "label": "Next Events",
                "order": 0,
                "defaultValue": "",
                "value": "",
                "className": "col-md-6",
                "useWidthPercentages": false,
                "widthPercentages": null,
                "readonly": false,
                "readonlyCondition": "",
                "placeholder": "",
                "required": false,
                "requiredCondition": "",
                "isMultiLine": false,
                "isInteger": false,
                "decimalPlace": 2,
                "expression": "",
                "additionalFilter": "",
                "oneDriveFileId": null,
                "isTodayValue": false,
                "isTodayValueCreated": true,
                "dateFormat": "mm/dd/yy hh:mm p",
                "timezone": null,
                "selectedDataGrid": null,
                "printedFileName": null,
                "dataFetchDepth": "basic",
                "buttonLabel": "",
                "dataForTemplate": null,
                "selectedOutputDataGrid": null,
                "templateRowKey": null,
                "isForDownload": true,
                "isOneDriveTemplate": false,
                "selectedOneDriveFile": null,
                "openInNewTab": true,
                "attachRecord": false,
                "isCurrentUser": false,
                "isCurrentUserOwner": true,
                "isNowTimeValue": false,
                "timeFormat": "HH:mm",
                "isMultiple": false,
                "isAjax": false,
                "dataOptions": [],
                "ajaxDataUrl": "",
                "isChecked": false,
                "vif": "",
                "customCode": "",
                "invisible": true,
                "invisibleCondition": "",
                "invisibleLabel": false,
                "enableCustomValidation": false,
                "customValidationRule": "",
                "customValidationErrorMessage": "",
                "mask": "",
                "lookupOpenInModalDisabled": false,
                "preventModalShowUpWhenNewItemAdded": false,
                "lookUpSearch": null,
                "editorMode": "javascript",
                "dataGridAvailableViews": [],
                "dataGridView": null,
                "dataGridAddRecordsText": "",
                "dataGridAddRecordText": "",
                "skipCrop": false,
                "disableRoundedStyle": false,
                "attachedFunction": "",
                "buttonText": "",
                "buttonVariant": "primary",
                "customClassName": "",
                "propName": "nextEvents"
              },
              {
                "type": "user",
                "name": "control_fb8f4240-3106-11f0-bcfe-05add1174dfb",
                "fieldName": "control_fb8f4240-3106-11f0-bcfe-05add1174dfb",
                "label": "Last edited by",
                "order": 0,
                "defaultValue": "",
                "value": "",
                "className": "col-md-6",
                "useWidthPercentages": false,
                "widthPercentages": null,
                "readonly": true,
                "readonlyCondition": "",
                "placeholder": "",
                "required": false,
                "requiredCondition": "",
                "isMultiLine": false,
                "isInteger": false,
                "decimalPlace": 2,
                "expression": "",
                "additionalFilter": "",
                "oneDriveFileId": null,
                "isTodayValue": false,
                "isTodayValueCreated": true,
                "dateFormat": "mm/dd/yy hh:mm p",
                "timezone": null,
                "selectedDataGrid": null,
                "printedFileName": null,
                "dataFetchDepth": "basic",
                "buttonLabel": "",
                "dataForTemplate": null,
                "selectedOutputDataGrid": null,
                "templateRowKey": null,
                "isForDownload": true,
                "isOneDriveTemplate": false,
                "selectedOneDriveFile": null,
                "openInNewTab": true,
                "attachRecord": false,
                "isCurrentUser": false,
                "isCurrentUserOwner": true,
                "isNowTimeValue": false,
                "timeFormat": "HH:mm",
                "isMultiple": false,
                "isAjax": false,
                "dataOptions": [],
                "ajaxDataUrl": "",
                "isChecked": false,
                "vif": "",
                "customCode": "",
                "invisible": true,
                "invisibleCondition": "",
                "invisibleLabel": false,
                "enableCustomValidation": false,
                "customValidationRule": "",
                "customValidationErrorMessage": "",
                "mask": "",
                "lookupOpenInModalDisabled": false,
                "preventModalShowUpWhenNewItemAdded": false,
                "lookUpSearch": null,
                "editorMode": "javascript",
                "dataGridAvailableViews": [],
                "dataGridView": null,
                "dataGridAddRecordsText": "",
                "dataGridAddRecordText": "",
                "skipCrop": false,
                "disableRoundedStyle": false,
                "attachedFunction": "",
                "buttonText": "",
                "buttonVariant": "primary",
                "customClassName": "",
                "propName": "lastEditedBy"
              },
              {
                "type": "datepicker",
                "name": "control_fbadedd0-3106-11f0-bcfe-05add1174dfb",
                "fieldName": "control_fbadedd0-3106-11f0-bcfe-05add1174dfb",
                "label": "Last edit date",
                "order": 0,
                "defaultValue": "",
                "value": "",
                "className": "col-md-6",
                "useWidthPercentages": false,
                "widthPercentages": null,
                "readonly": true,
                "readonlyCondition": "",
                "placeholder": "",
                "required": false,
                "requiredCondition": "",
                "isMultiLine": false,
                "isInteger": false,
                "decimalPlace": 2,
                "expression": "",
                "additionalFilter": "",
                "oneDriveFileId": null,
                "isTodayValue": false,
                "isTodayValueCreated": true,
                "dateFormat": "mm/dd/yy hh:mm p",
                "timezone": null,
                "selectedDataGrid": null,
                "printedFileName": null,
                "dataFetchDepth": "basic",
                "buttonLabel": "",
                "dataForTemplate": null,
                "selectedOutputDataGrid": null,
                "templateRowKey": null,
                "isForDownload": true,
                "isOneDriveTemplate": false,
                "selectedOneDriveFile": null,
                "openInNewTab": true,
                "attachRecord": false,
                "isCurrentUser": false,
                "isCurrentUserOwner": true,
                "isNowTimeValue": false,
                "timeFormat": "HH:mm",
                "isMultiple": false,
                "isAjax": false,
                "dataOptions": [],
                "ajaxDataUrl": "",
                "isChecked": false,
                "vif": "",
                "customCode": "",
                "invisible": true,
                "invisibleCondition": "",
                "invisibleLabel": false,
                "enableCustomValidation": false,
                "customValidationRule": "",
                "customValidationErrorMessage": "",
                "mask": "",
                "lookupOpenInModalDisabled": false,
                "preventModalShowUpWhenNewItemAdded": false,
                "lookUpSearch": null,
                "editorMode": "javascript",
                "dataGridAvailableViews": [],
                "dataGridView": null,
                "dataGridAddRecordsText": "",
                "dataGridAddRecordText": "",
                "skipCrop": false,
                "disableRoundedStyle": false,
                "attachedFunction": "",
                "buttonText": "",
                "buttonVariant": "primary",
                "customClassName": "",
                "propName": "lastEditDate"
              }
            ]
          }
        ]
      }
    ],
    "layout": "collapse"
  },
  "source": "importtest",
  "storageType": "dashboard",
  "title": "import test"
}